states/__init__.py
states/states.py
states/territories.py
states/__pycache__/states.cpython-38.pyc
states/data/__init__.py
states/data/states.json
states/data/states_data.py
states/data/territories.json
states/data/territories_data.py
unitedstates-0.0.1.7.dist-info/LICENSE
unitedstates-0.0.1.7.dist-info/METADATA
unitedstates-0.0.1.7.dist-info/WHEEL
unitedstates-0.0.1.7.dist-info/top_level.txt
unitedstates-0.0.1.7.dist-info/RECORD
