Metadata-Version: 2.1
Name: unitedstates
Version: 0.0.1.7
Summary: Package that provides information about U.S states and territories.
Home-page: https://github.com/AColocho/us-states
Author: Alejandro Colocho
Author-email: a.colocho@outlook.com
License: Boost Software License
Platform: UNKNOWN
Classifier: Programming Language :: Python :: 3
Classifier: Operating System :: OS Independent
Requires-Python: >=3.7
